international_urns/__init__.py
international_urns/base.py
international_urns/builtin.py
international_urns/discovery.py
international_urns/extractors.py
international_urns/extractors_registry.py
international_urns/generators.py
international_urns/generators_registry.py
international_urns/input_sanitizer.py
international_urns/normalization.py
international_urns/py.typed
international_urns/registry_context.py
international_urns/validators.py
international_urns/validators_registry.py
international_urns-1.0.1.dist-info/METADATA
international_urns-1.0.1.dist-info/WHEEL
international_urns-1.0.1.dist-info/licenses/LICENSE
international_urns-1.0.1.dist-info/RECORD
