Metadata-Version: 2.4
Name: international-urns
Version: 1.0.1
Summary: A microkernel-based library for validating country-specific URN formats
Project-URL: Homepage, https://gitlab.com/Kencho1/international-urns
Project-URL: Repository, https://gitlab.com/Kencho1/international-urns
Project-URL: Issues, https://gitlab.com/Kencho1/international-urns/-/issues
Author: Jesús Alonso Abad
License-Expression: MIT
License-File: LICENSE
Classifier: Development Status :: 4 - Beta
Classifier: Intended Audience :: Developers
Classifier: License :: OSI Approved :: MIT License
Classifier: Programming Language :: Python :: 3
Classifier: Programming Language :: Python :: 3.11
Classifier: Programming Language :: Python :: 3.12
Classifier: Programming Language :: Python :: 3.13
Classifier: Programming Language :: Python :: 3.14
Classifier: Typing :: Typed
Requires-Python: >=3.11
Requires-Dist: urnparse>=0.2.0
Provides-Extra: test
Requires-Dist: faker>=24.0.0; extra == 'test'
Requires-Dist: mypy>=1.11.0; extra == 'test'
Requires-Dist: pydantic>=2.0.0; extra == 'test'
Requires-Dist: pytest-cov>=4.1.0; extra == 'test'
Requires-Dist: pytest>=8.0.0; extra == 'test'
Requires-Dist: ruff>=0.6.0; extra == 'test'
